siarnaq/__init__.py
siarnaq/degrees.py
siarnaq/distances.py
tests/__init__.py
tests/test_degrees.py
tests/test_distances.py
siarnaq-1.0.1.dist-info/AUTHORS.md
siarnaq-1.0.1.dist-info/LICENSE.md
siarnaq-1.0.1.dist-info/METADATA
siarnaq-1.0.1.dist-info/WHEEL
siarnaq-1.0.1.dist-info/top_level.txt
siarnaq-1.0.1.dist-info/RECORD
