Metadata-Version: 2.1
Name: siarnaq
Version: 1.0.1
Summary: A conversion library
Home-page: https://github.com/thierrydecker/siarnaq
Author: Thierry P.G. DECKER
Author-email: mail@thierry-decker.com
License: UNKNOWN
Platform: UNKNOWN
Classifier: Programming Language :: Python :: 3
Classifier: License :: OSI Approved :: MIT License
Classifier: Operating System :: OS Independent
Requires-Python: >=3.8
